EasyPyRequests.py
easypyrequests-1.0.0.dist-info/WHEEL
easypyrequests-1.0.0.dist-info/METADATA
easypyrequests-1.0.0.dist-info/RECORD
