Metadata-Version: 2.1
Name: easypyrequests
Version: 1.0.0
Summary: Requests Library for easy format
Author: DragonWolf
Author-email: officialdragonwolf@gmail.com
Requires-Python: >=3.8,<4.0
Classifier: Programming Language :: Python :: 3
Classifier: Programming Language :: Python :: 3.8
Classifier: Programming Language :: Python :: 3.9
